<?xml version="1.0" encoding="ISO-8859-1"?>
<EnvioDTE xmlns="http://www.sii.cl/SiiDte" xmlns:xsi="http://www.w3.org/2001/XMLSchema-instance" xsi:schemaLocation="http://www.sii.cl/SiiDte EnvioDTE_v10.xsd" version="1.0">
  <SetDTE ID="SetDoc">
    <Caratula version="1.0">
      <RutEmisor>77748100-2</RutEmisor>
      <RutEnvia>3615086-6</RutEnvia>
      <RutReceptor>60803000-K</RutReceptor>
      <FchResol>2014-08-22</FchResol>
      <NroResol>80</NroResol>
      <TmstFirmaEnv>2016-08-09T10:30:33</TmstFirmaEnv>
      <SubTotDTE>
        <TpoDTE>52</TpoDTE>
        <NroDTE>1</NroDTE>
      </SubTotDTE>
    </Caratula>
    <DTE version="1.0">
  <Documento ID="T52F2">
    <Encabezado>
      <IdDoc>
        <TipoDTE>52</TipoDTE>
        <Folio>2</Folio>
        <FchEmis>2016-08-09</FchEmis>
      </IdDoc>
      <Emisor>
        <RUTEmisor>77748100-2</RUTEmisor>
        <RznSoc>SOC COM DE TRANSP INDUST Y DE INVERS VIBRADOS CHILE LIMITADA</RznSoc>
        <GiroEmis>VENTA AL POR MENOR DE ARTICULOS DE FERRETERIA</GiroEmis>
        <Acteco>523410</Acteco>
        <DirOrigen>CIENFUEGOS 1595</DirOrigen>
        <CmnaOrigen>SAN JAVIER</CmnaOrigen>
      </Emisor>
      <Receptor>
        <RUTRecep>76509207-8</RUTRecep>
        <RznSocRecep>CONSTRUCTORA  ALTOS DE LONCOMILLA SPA</RznSocRecep>
        <GiroRecep>OBRAS MENORES EN CONSTRUCCIÓN (CONTRATI</GiroRecep>
        <DirRecep>CALLE DOMINGO PEREZ 6 SOLAR DE LONCOMILLA</DirRecep>
        <CmnaRecep>SAN JAVIER</CmnaRecep>
      </Receptor>
      <Totales>
        <MntNeto>82740</MntNeto>
        <TasaIVA>19</TasaIVA>
        <IVA>15721</IVA>
        <MntTotal>98461</MntTotal>
      </Totales>
    </Encabezado>
    <Detalle>
      <NroLinDet>1</NroLinDet>
      <NmbItem>BARRA FE LISO 6mmx6mt A-44 OFERTA            </NmbItem>
      <QtyItem>8.00</QtyItem>
      <PrcItem>690</PrcItem>
      <MontoItem>5520</MontoItem>
    </Detalle>
    <Detalle>
      <NroLinDet>2</NroLinDet>
      <NmbItem>BARRA FE ESTR.A-44 12mmx6mt OFERTA           </NmbItem>
      <QtyItem>6.00</QtyItem>
      <PrcItem>2750</PrcItem>
      <MontoItem>16500</MontoItem>
    </Detalle>
    <Detalle>
      <NroLinDet>3</NroLinDet>
      <NmbItem>SOLDADURA 3/32 P/AZUL 230-S INDURA           </NmbItem>
      <QtyItem>1.00</QtyItem>
      <PrcItem>3460</PrcItem>
      <MontoItem>3460</MontoItem>
    </Detalle>
    <Detalle>
      <NroLinDet>4</NroLinDet>
      <NmbItem>BARRA FE ESTR.A-44 8mmx6mts OFERTA           </NmbItem>
      <QtyItem>3.00</QtyItem>
      <PrcItem>1220</PrcItem>
      <MontoItem>3660</MontoItem>
    </Detalle>
    <Detalle>
      <NroLinDet>5</NroLinDet>
      <NmbItem>PL TERCIADO ESTR.12mm 1.22x2.44mts           </NmbItem>
      <QtyItem>4.00</QtyItem>
      <PrcItem>13400</PrcItem>
      <MontoItem>53600</MontoItem>
    </Detalle>
    <TED version="1.0">
  <DD>
    <RE>77748100-2</RE>
    <TD>52</TD>
    <F>2</F>
    <FE>2016-08-09</FE>
    <RR>76509207-8</RR>
    <RSR>CONSTRUCTORA  ALTOS DE LONCOMILLA SPA</RSR>
    <MNT>98461</MNT>
    <IT1>BARRA FE LISO 6mmx6mt A-44 OFERTA       </IT1>
    <CAF version="1.0">
<DA>
<RE>77748100-2</RE>
<RS>SOC COM DE TRANSP INDUST Y DE INVERS VIB</RS>
<TD>52</TD>
<RNG><D>1</D><H>10000</H></RNG>
<FA>2016-08-05</FA>
<RSAPK><M>0MESkMkbpR05JGyWvt76jUprXDRXujztkKkVQlD6zTyazMB8mxi5cNyubF3O0C4s61wOH9LKCzFp3eeKpGaznQ==</M><E>Aw==</E></RSAPK>
<IDK>300</IDK>
</DA>
<FRMA algoritmo="SHA1withRSA">BTpF3OyQIJk1pl9RBAXyPjk6jsd8Ql0taSTzAiTDsNGvr98RHhBZkujO1emILJb9qjqvpc2DOc70jxrMRnp8lg==</FRMA>
</CAF>
    <TSTED>2016-08-09T10:30:33</TSTED>
  </DD>
  <FRMT algoritmo="SHA1withRSA">zzGXS0za4BZGcNL+8dI25kaI9vzbYsPHpi2UH5DYWOc9P/nQegrVrZHwpyK4lnGoIkoN1xRLlHvOCuGegalMLg==</FRMT>
</TED>
  <TmstFirma>2016-08-09T10:30:33</TmstFirma></Documento>
<Signature xmlns="http://www.w3.org/2000/09/xmldsig#"><SignedInfo xmlns="http://www.w3.org/2000/09/xmldsig#"><CanonicalizationMethod Algorithm="http://www.w3.org/TR/2001/REC-xml-c14n-20010315"/><SignatureMethod Algorithm="http://www.w3.org/2000/09/xmldsig#rsa-sha1"/><Reference URI="#T52F2"><Transforms><Transform Algorithm="http://www.w3.org/2000/09/xmldsig#enveloped-signature"/></Transforms><DigestMethod Algorithm="http://www.w3.org/2000/09/xmldsig#sha1"/><DigestValue>rIzkylUMS7RbxgQKvl9ILphTtTY=</DigestValue></Reference></SignedInfo><SignatureValue>A3gzFonj4K42WtN0ZlZi1rUjpdzJH+4jBNFxMvs93N++SIbmFvQk9jC3ckIaLMlH
imnfqKs1Rrn6ZrL/wgOiJyXElRvq9QjL6qMzTQMiDRB6QraGTBje1qZwa8KPyOWT
lfcUvGytoiXLlOO6WKsZxDT7+WDxQHL0vAQifEU8MqO8y2GYzRnsdhJ0SE2XGN3e
5y40Pwsund9Uo920DMFLWDAcG18ZCqoJfmGIxRrQ5Hjfo5IRfytxky73xdQvHIeD
DnHGfhsiUoAzo9g5y6cboKqq3MSV+trL3lQMykWX8HiZxh0u4KsbxprvpFFpNbPN
eHGDDreGRsZd1Jt+uTFraw==</SignatureValue><KeyInfo><KeyValue><RSAKeyValue><Modulus>1E+JkMFO8vGBrEVQAuNy6j1cjrl/zZRoxNE/TFvUoTOowhVCxm7IL0wR3KJ3FuYD
D+2fJ+/uGaPywU/ydZzlx6Dl+1IkjeVJ7G1FmXMmQZ/XmQV7zTRWeL3+qtbfq5Nn
x2BpS5scdWZ7zxVL0aYNO0+LnmnwAbn5ese2AxG0+KSbTEcpT2D1bIGsDxWDzhRq
jlYe2HaR4hP/lWZkeStDscStCJE+ENB0Ko2qioEzohV4zqzH9Mhe4ht1jbSDu/U9
EsyFM5krU/1wT6UnoWjrExPuHnN5U2xZSNu11gQpp13zGlfCC9rtcFmLxdrPUWay
N4QPT0qVjMBa+SNQ8Ouxpw==</Modulus><Exponent>AQAB</Exponent></RSAKeyValue></KeyValue><X509Data><X509Certificate>MIIF1jCCBL6gAwIBAgICZ34wDQYJKoZIhvcNAQEFBQAwgaYxCzAJBgNVBAYTAkNM
MRgwFgYDVQQKEw9BY2VwdGEuY29tIFMuQS4xSDBGBgNVBAMTP0FjZXB0YS5jb20g
QXV0b3JpZGFkIENlcnRpZmljYWRvcmEgQ2xhc2UgMiBQZXJzb25hIE5hdHVyYWwg
LSBHMzEeMBwGCSqGSIb3DQEJARYPaW5mb0BhY2VwdGEuY29tMRMwEQYDVQQFEwo5
NjkxOTA1MC04MB4XDTE2MDcxODE5MzA1MVoXDTE5MDcxODE5MzA1MVowgYYxCzAJ
BgNVBAYTAkNMMRgwFgYDVQQMEw9QRVJTT05BIE5BVFVSQUwxIjAgBgNVBAMTGVZJ
VEVSQk8gQkFSUklFTlRPUyBBWk9DQVIxJTAjBgkqhkiG9w0BCQEWFklORk9WSUJS
QURPU0BHTUFJTC5DT00xEjAQBgNVBAUTCTM2MTUwODYtNjCCASIwDQYJKoZIhvcN
AQEBBQADggEPADCCAQoCggEBANRPiZDBTvLxgaxFUALjcuo9XI65f82UaMTRP0xb
1KEzqMIVQsZuyC9MEdyidxbmAw/tnyfv7hmj8sFP8nWc5ceg5ftSJI3lSextRZlz
JkGf15kFe800Vni9/qrW36uTZ8dgaUubHHVme88VS9GmDTtPi55p8AG5+XrHtgMR
tPikm0xHKU9g9WyBrA8Vg84Uao5WHth2keIT/5VmZHkrQ7HErQiRPhDQdCqNqoqB
M6IVeM6sx/TIXuIbdY20g7v1PRLMhTOZK1P9cE+lJ6Fo6xMT7h5zeVNsWUjbtdYE
Kadd8xpXwgva7XBZi8Xaz1FmsjeED09KlYzAWvkjUPDrsacCAwEAAaOCAiowggIm
MB8GA1UdIwQYMBaAFEAkGj2pMXqFd3o9nnKTOYTlQDgZMB0GA1UdDgQWBBR8VdNA
sAkYc3h1hQJjOw4gG1G67TALBgNVHQ8EBAMCBPAwHQYDVR0lBBYwFAYIKwYBBQUH
AwIGCCsGAQUFBwMEMBEGCWCGSAGG+EIBAQQEAwIFoDBuBgNVHSAEZzBlMGMGCisG
AQQBtWuHagowVTAoBggrBgEFBQcCARYcaHR0cDovL3d3dy5hY2VwdGEuY29tL0NQ
Uy1HMzApBggrBgEFBQcCAjAdMBYWD0FjZXB0YS5jb20gUy5BLjADAgEJGgNUQkQw
WgYDVR0SBFMwUaAYBggrBgEEAcEBAqAMFgo5NjkxOTA1MC04oCQGCCsGAQUFBwgD
oBgwFgwKOTY5MTkwNTAtOAYIKwYBBAHBAQKBD2luZm9AYWNlcHRhLmNvbTBfBgNV
HREEWDBWoBcGCCsGAQQBwQEBoAsWCTM2MTUwODYtNqAjBggrBgEFBQcIA6AXMBUM
CTM2MTUwODYtNgYIKwYBBAHBAQKBFklORk9WSUJSQURPU0BHTUFJTC5DT00wPwYI
KwYBBQUHAQEEMzAxMC8GCCsGAQUFBzABhiNodHRwOi8vb2NzcC5hY2VwdGEuY29t
L0NsYXNlM0Jpby1HMzA3BgNVHR8EMDAuMCygKqAohiZodHRwOi8vY3JsLmFjZXB0
YS5jb20vQ2xhc2UzQmlvLUczLmNybDANBgkqhkiG9w0BAQUFAAOCAQEA5glFPIYl
U46mZopX2UZMbpycGXBOOldQvn4mSHaOIadwqoS3MS2zKq6yNYyStzBw8/V7zzOB
C/PR2xXKLZ0F0RvsorvaYen9UJexIw9jqYeBaoJouzIWxngDmJ88NjIM8i2Nq8Dj
0dTX5to8y5z3+j2IErIt1PS4/FPU8ijq9vLBRG+QIbPlvvlejksxQss+crENQ6yB
SrVN5o0wylC+bQ8/d1Tw/DZubHthEZ4ZEx0VpNbh/yO8nfLJ53k/gejAUDXubc5v
3kepNlruRPiJtwFuxDyorJAHVBlRLqraORuHd/NM5m/9DrSXIox+PHOw7xfCmHI9
mrPfGW7p6Y6JNQ==</X509Certificate></X509Data></KeyInfo></Signature></DTE>
  </SetDTE>
<Signature xmlns="http://www.w3.org/2000/09/xmldsig#"><SignedInfo xmlns="http://www.w3.org/2000/09/xmldsig#" xmlns:xsi="http://www.w3.org/2001/XMLSchema-instance"><CanonicalizationMethod Algorithm="http://www.w3.org/TR/2001/REC-xml-c14n-20010315"/><SignatureMethod Algorithm="http://www.w3.org/2000/09/xmldsig#rsa-sha1"/><Reference URI="#SetDoc"><Transforms><Transform Algorithm="http://www.w3.org/2000/09/xmldsig#enveloped-signature"/></Transforms><DigestMethod Algorithm="http://www.w3.org/2000/09/xmldsig#sha1"/><DigestValue>p9/Wi8TbX0CHr2m3B5lz8Mx50YM=</DigestValue></Reference></SignedInfo><SignatureValue>OogOt0z61JDEhW8U4gtRLnThZTo/60p9+dDOvPU+cR69GszUstmDRMZF6U0Le/cK
+Yi6OvaH2UPX/cdRj9xM6KVcnGc86u0rdG4oaqim90v4BT6PR8vZXq8DQVQeEIw2
ZOfCMqmHjmoMQlZ1mA3eV7S7TUMHBTe8CqA8sQaVEXYPfooCqbOhwPhPfkUnA8Gk
4Oibm3uE8z3ITtL00GQGyL1gKTSgzcV2T4sPkyIzP3iMLvZkv6HiQmKOV/bNrFsS
Z1L0r0i/2nkRyE1UH0wxtozlpesN4xyY8aBBFLKJvwhyTrvq8QkdiNj5D9J5njT+
AxIdrnP19obsHQ/s2dX3IA==</SignatureValue><KeyInfo><KeyValue><RSAKeyValue><Modulus>1E+JkMFO8vGBrEVQAuNy6j1cjrl/zZRoxNE/TFvUoTOowhVCxm7IL0wR3KJ3FuYD
D+2fJ+/uGaPywU/ydZzlx6Dl+1IkjeVJ7G1FmXMmQZ/XmQV7zTRWeL3+qtbfq5Nn
x2BpS5scdWZ7zxVL0aYNO0+LnmnwAbn5ese2AxG0+KSbTEcpT2D1bIGsDxWDzhRq
jlYe2HaR4hP/lWZkeStDscStCJE+ENB0Ko2qioEzohV4zqzH9Mhe4ht1jbSDu/U9
EsyFM5krU/1wT6UnoWjrExPuHnN5U2xZSNu11gQpp13zGlfCC9rtcFmLxdrPUWay
N4QPT0qVjMBa+SNQ8Ouxpw==</Modulus><Exponent>AQAB</Exponent></RSAKeyValue></KeyValue><X509Data><X509Certificate>MIIF1jCCBL6gAwIBAgICZ34wDQYJKoZIhvcNAQEFBQAwgaYxCzAJBgNVBAYTAkNM
MRgwFgYDVQQKEw9BY2VwdGEuY29tIFMuQS4xSDBGBgNVBAMTP0FjZXB0YS5jb20g
QXV0b3JpZGFkIENlcnRpZmljYWRvcmEgQ2xhc2UgMiBQZXJzb25hIE5hdHVyYWwg
LSBHMzEeMBwGCSqGSIb3DQEJARYPaW5mb0BhY2VwdGEuY29tMRMwEQYDVQQFEwo5
NjkxOTA1MC04MB4XDTE2MDcxODE5MzA1MVoXDTE5MDcxODE5MzA1MVowgYYxCzAJ
BgNVBAYTAkNMMRgwFgYDVQQMEw9QRVJTT05BIE5BVFVSQUwxIjAgBgNVBAMTGVZJ
VEVSQk8gQkFSUklFTlRPUyBBWk9DQVIxJTAjBgkqhkiG9w0BCQEWFklORk9WSUJS
QURPU0BHTUFJTC5DT00xEjAQBgNVBAUTCTM2MTUwODYtNjCCASIwDQYJKoZIhvcN
AQEBBQADggEPADCCAQoCggEBANRPiZDBTvLxgaxFUALjcuo9XI65f82UaMTRP0xb
1KEzqMIVQsZuyC9MEdyidxbmAw/tnyfv7hmj8sFP8nWc5ceg5ftSJI3lSextRZlz
JkGf15kFe800Vni9/qrW36uTZ8dgaUubHHVme88VS9GmDTtPi55p8AG5+XrHtgMR
tPikm0xHKU9g9WyBrA8Vg84Uao5WHth2keIT/5VmZHkrQ7HErQiRPhDQdCqNqoqB
M6IVeM6sx/TIXuIbdY20g7v1PRLMhTOZK1P9cE+lJ6Fo6xMT7h5zeVNsWUjbtdYE
Kadd8xpXwgva7XBZi8Xaz1FmsjeED09KlYzAWvkjUPDrsacCAwEAAaOCAiowggIm
MB8GA1UdIwQYMBaAFEAkGj2pMXqFd3o9nnKTOYTlQDgZMB0GA1UdDgQWBBR8VdNA
sAkYc3h1hQJjOw4gG1G67TALBgNVHQ8EBAMCBPAwHQYDVR0lBBYwFAYIKwYBBQUH
AwIGCCsGAQUFBwMEMBEGCWCGSAGG+EIBAQQEAwIFoDBuBgNVHSAEZzBlMGMGCisG
AQQBtWuHagowVTAoBggrBgEFBQcCARYcaHR0cDovL3d3dy5hY2VwdGEuY29tL0NQ
Uy1HMzApBggrBgEFBQcCAjAdMBYWD0FjZXB0YS5jb20gUy5BLjADAgEJGgNUQkQw
WgYDVR0SBFMwUaAYBggrBgEEAcEBAqAMFgo5NjkxOTA1MC04oCQGCCsGAQUFBwgD
oBgwFgwKOTY5MTkwNTAtOAYIKwYBBAHBAQKBD2luZm9AYWNlcHRhLmNvbTBfBgNV
HREEWDBWoBcGCCsGAQQBwQEBoAsWCTM2MTUwODYtNqAjBggrBgEFBQcIA6AXMBUM
CTM2MTUwODYtNgYIKwYBBAHBAQKBFklORk9WSUJSQURPU0BHTUFJTC5DT00wPwYI
KwYBBQUHAQEEMzAxMC8GCCsGAQUFBzABhiNodHRwOi8vb2NzcC5hY2VwdGEuY29t
L0NsYXNlM0Jpby1HMzA3BgNVHR8EMDAuMCygKqAohiZodHRwOi8vY3JsLmFjZXB0
YS5jb20vQ2xhc2UzQmlvLUczLmNybDANBgkqhkiG9w0BAQUFAAOCAQEA5glFPIYl
U46mZopX2UZMbpycGXBOOldQvn4mSHaOIadwqoS3MS2zKq6yNYyStzBw8/V7zzOB
C/PR2xXKLZ0F0RvsorvaYen9UJexIw9jqYeBaoJouzIWxngDmJ88NjIM8i2Nq8Dj
0dTX5to8y5z3+j2IErIt1PS4/FPU8ijq9vLBRG+QIbPlvvlejksxQss+crENQ6yB
SrVN5o0wylC+bQ8/d1Tw/DZubHthEZ4ZEx0VpNbh/yO8nfLJ53k/gejAUDXubc5v
3kepNlruRPiJtwFuxDyorJAHVBlRLqraORuHd/NM5m/9DrSXIox+PHOw7xfCmHI9
mrPfGW7p6Y6JNQ==</X509Certificate></X509Data></KeyInfo></Signature></EnvioDTE>
