<?xml version="1.0" encoding="ISO-8859-1"?>
<EnvioDTE xmlns="http://www.sii.cl/SiiDte" xmlns:xsi="http://www.w3.org/2001/XMLSchema-instance" xsi:schemaLocation="http://www.sii.cl/SiiDte EnvioDTE_v10.xsd" version="1.0">
  <SetDTE ID="SetDoc">
    <Caratula version="1.0">
      <RutEmisor>77748100-2</RutEmisor>
      <RutEnvia>3615086-6</RutEnvia>
      <RutReceptor>60803000-K</RutReceptor>
      <FchResol>2014-08-22</FchResol>
      <NroResol>80</NroResol>
      <TmstFirmaEnv>2016-09-05T11:02:48</TmstFirmaEnv>
      <SubTotDTE>
        <TpoDTE>33</TpoDTE>
        <NroDTE>1</NroDTE>
      </SubTotDTE>
    </Caratula>
    <DTE version="1.0">
  <Documento ID="T33F911">
    <Encabezado>
      <IdDoc>
        <TipoDTE>33</TipoDTE>
        <Folio>911</Folio>
        <FchEmis>2016-09-05</FchEmis>
      </IdDoc>
      <Emisor>
        <RUTEmisor>77748100-2</RUTEmisor>
        <RznSoc>SOC COM DE TRANSP INDUST Y DE INVERS VIBRADOS CHILE LIMITADA</RznSoc>
        <GiroEmis>Venta al por menor de articulos de Ferreteria  Fono: 732321100   mail: infovibra</GiroEmis>
        <Acteco>523410</Acteco>
        <DirOrigen>Cienfuegos 1595  Suc: Ruta 5 Sur Km 277 Cruce Pangal</DirOrigen>
        <CmnaOrigen>SAN JAVIER</CmnaOrigen>
      </Emisor>
      <Receptor>
        <RUTRecep>8432690-9</RUTRecep>
        <RznSocRecep>RIVERO FUENTES OSCAR ANTONIO</RznSocRecep>
        <GiroRecep>VENTA AL POR MENOR DE ARTIçCULOS DE FER</GiroRecep>
        <DirRecep>BALMACEDA N¶349</DirRecep>
      </Receptor>
      <Totales>
        <MntNeto>444706</MntNeto>
        <TasaIVA>19</TasaIVA>
        <IVA>84494</IVA>
        <MntTotal>529200</MntTotal>
      </Totales>
    </Encabezado>
    <Detalle>
      <NroLinDet>1</NroLinDet>
      <NmbItem>ALAMBRE NYA 1,5mm BLANCO                     </NmbItem>
      <QtyItem>200.00</QtyItem>
      <PrcItem>84</PrcItem>
      <MontoItem>16807</MontoItem>
    </Detalle>
    <Detalle>
      <NroLinDet>2</NroLinDet>
      <NmbItem>ALAMBRE NYA 1,5mm ROJO                       </NmbItem>
      <QtyItem>200.00</QtyItem>
      <PrcItem>84</PrcItem>
      <MontoItem>16807</MontoItem>
    </Detalle>
    <Detalle>
      <NroLinDet>3</NroLinDet>
      <NmbItem>ALAMBRE NYA 1,5mm VERDE                      </NmbItem>
      <QtyItem>200.00</QtyItem>
      <PrcItem>84</PrcItem>
      <MontoItem>16807</MontoItem>
    </Detalle>
    <Detalle>
      <NroLinDet>4</NroLinDet>
      <NmbItem>CA•ERIA COBRE L 1/2" EPC /CONMET                </NmbItem>
      <QtyItem>12.00</QtyItem>
      <PrcItem>11806</PrcItem>
      <MontoItem>141681</MontoItem>
    </Detalle>
    <Detalle>
      <NroLinDet>5</NroLinDet>
      <NmbItem>CA•ERIA COBRE AGUA 3/4" EPC /CONMET                 </NmbItem>
      <QtyItem>6.00</QtyItem>
      <PrcItem>14613</PrcItem>
      <MontoItem>87681</MontoItem>
    </Detalle>
    <Detalle>
      <NroLinDet>6</NroLinDet>
      <NmbItem>TUBO SAN.GRIS 75mm TIGRE CERTIF.             </NmbItem>
      <QtyItem>12.00</QtyItem>
      <PrcItem>4285</PrcItem>
      <MontoItem>51429</MontoItem>
    </Detalle>
    <Detalle>
      <NroLinDet>7</NroLinDet>
      <NmbItem>TUBO SAN.GRIS 40mm TIGRE CERTIF.             </NmbItem>
      <QtyItem>12.00</QtyItem>
      <PrcItem>2168</PrcItem>
      <MontoItem>26017</MontoItem>
    </Detalle>
    <Detalle>
      <NroLinDet>8</NroLinDet>
      <NmbItem>TUBO PVC HID.25mmC12.5 TIGRE                 </NmbItem>
      <QtyItem>20.00</QtyItem>
      <PrcItem>1596</PrcItem>
      <MontoItem>31933</MontoItem>
    </Detalle>
    <Detalle>
      <NroLinDet>9</NroLinDet>
      <NmbItem>CA•ON GALV.LISO 4"                           </NmbItem>
      <QtyItem>10.00</QtyItem>
      <PrcItem>1722</PrcItem>
      <MontoItem>17227</MontoItem>
    </Detalle>
    <Detalle>
      <NroLinDet>10</NroLinDet>
      <NmbItem>CA•ON GALV.LISO 4 1/2"                       </NmbItem>
      <QtyItem>10.00</QtyItem>
      <PrcItem>1840</PrcItem>
      <MontoItem>18403</MontoItem>
    </Detalle>
    <Detalle>
      <NroLinDet>11</NroLinDet>
      <NmbItem>CA•ON GALV.LISO 4 3/4"                       </NmbItem>
      <QtyItem>10.00</QtyItem>
      <PrcItem>1991</PrcItem>
      <MontoItem>19916</MontoItem>
    </Detalle>
    <TED version="1.0">
  <DD>
    <RE>77748100-2</RE>
    <TD>33</TD>
    <F>911</F>
    <FE>2016-09-05</FE>
    <RR>8432690-9</RR>
    <RSR>RIVERO FUENTES OSCAR ANTONIO</RSR>
    <MNT>529200</MNT>
    <IT1>ALAMBRE NYA 1,5mm BLANCO</IT1>
    <CAF version="1.0">
<DA>
<RE>77748100-2</RE>
<RS>SOC COM DE TRANSP INDUST Y DE INVERS VIB</RS>
<TD>33</TD>
<RNG><D>1</D><H>1400</H></RNG>
<FA>2016-08-05</FA>
<RSAPK><M>vATV3PWobLnIU1vVeHRAv7XhHp0EIfOGntSNsJ8Y4GPqSZvjfktKnR5SqdR8vApojZzxZ2HrUGI7fakff9hybw==</M><E>Aw==</E></RSAPK>
<IDK>300</IDK>
</DA>
<FRMA algoritmo="SHA1withRSA">KAOFDPci4cikJaWgnJ8/K1tgsjoSG0UKewo6M4w53bceABYZ3NUk1miGkbzqrxIZ2JkxTez7iJ4y0eOt14nwwg==</FRMA>
</CAF>
    <TSTED>2016-09-05T11:02:48</TSTED>
  </DD>
  <FRMT algoritmo="SHA1withRSA">hcb+Zi5BWolHxzmGSrlGF0Q8JbkUmoGSQfWMVqeYVOHqHOtucSlgtK1oZaqDoyyv78Ne2Ub8sxTTJkM+8B9tog==</FRMT>
</TED>
  <TmstFirma>2016-09-05T11:02:48</TmstFirma></Documento>
<Signature xmlns="http://www.w3.org/2000/09/xmldsig#"><SignedInfo xmlns="http://www.w3.org/2000/09/xmldsig#"><CanonicalizationMethod Algorithm="http://www.w3.org/TR/2001/REC-xml-c14n-20010315"/><SignatureMethod Algorithm="http://www.w3.org/2000/09/xmldsig#rsa-sha1"/><Reference URI="#T33F911"><Transforms><Transform Algorithm="http://www.w3.org/2000/09/xmldsig#enveloped-signature"/></Transforms><DigestMethod Algorithm="http://www.w3.org/2000/09/xmldsig#sha1"/><DigestValue>joDPY5/a4tPudW09A94h9OsCdcU=</DigestValue></Reference></SignedInfo><SignatureValue>dTU6nhFjQSyyBflvlHu03qEMlZ3F7cOm7/b9Bhil/eUBk5WdLZLO5y+HCupODSss
hWWBn37oA3bE2esK/N+Higwd/StC1mfgNF6H9xuemji0mRnz6hGHeXtb1R8Uqrp4
lhmY/v7jTRhT8oVWGBkkhXWzjLAXmLdNu5Gia5qgHCj/25mYtQq5NHmSKlBJNcTq
ZT7pFYRF+/yMgfWhiP5U+e7LljGDG/ZjEXPKL3qoJRmCqoPZPzJRERyeenb+bmtC
2VjAGD76FzNI/o6ly+cHL7T6H0B8kQd4F1qTKvJfOmYCxE73WK1v3egG7Qi5x4kA
m/dm8n2bDmJ0zWl4gDEEUA==</SignatureValue><KeyInfo><KeyValue><RSAKeyValue><Modulus>1E+JkMFO8vGBrEVQAuNy6j1cjrl/zZRoxNE/TFvUoTOowhVCxm7IL0wR3KJ3FuYD
D+2fJ+/uGaPywU/ydZzlx6Dl+1IkjeVJ7G1FmXMmQZ/XmQV7zTRWeL3+qtbfq5Nn
x2BpS5scdWZ7zxVL0aYNO0+LnmnwAbn5ese2AxG0+KSbTEcpT2D1bIGsDxWDzhRq
jlYe2HaR4hP/lWZkeStDscStCJE+ENB0Ko2qioEzohV4zqzH9Mhe4ht1jbSDu/U9
EsyFM5krU/1wT6UnoWjrExPuHnN5U2xZSNu11gQpp13zGlfCC9rtcFmLxdrPUWay
N4QPT0qVjMBa+SNQ8Ouxpw==</Modulus><Exponent>AQAB</Exponent></RSAKeyValue></KeyValue><X509Data><X509Certificate>MIIF1jCCBL6gAwIBAgICZ34wDQYJKoZIhvcNAQEFBQAwgaYxCzAJBgNVBAYTAkNM
MRgwFgYDVQQKEw9BY2VwdGEuY29tIFMuQS4xSDBGBgNVBAMTP0FjZXB0YS5jb20g
QXV0b3JpZGFkIENlcnRpZmljYWRvcmEgQ2xhc2UgMiBQZXJzb25hIE5hdHVyYWwg
LSBHMzEeMBwGCSqGSIb3DQEJARYPaW5mb0BhY2VwdGEuY29tMRMwEQYDVQQFEwo5
NjkxOTA1MC04MB4XDTE2MDcxODE5MzA1MVoXDTE5MDcxODE5MzA1MVowgYYxCzAJ
BgNVBAYTAkNMMRgwFgYDVQQMEw9QRVJTT05BIE5BVFVSQUwxIjAgBgNVBAMTGVZJ
VEVSQk8gQkFSUklFTlRPUyBBWk9DQVIxJTAjBgkqhkiG9w0BCQEWFklORk9WSUJS
QURPU0BHTUFJTC5DT00xEjAQBgNVBAUTCTM2MTUwODYtNjCCASIwDQYJKoZIhvcN
AQEBBQADggEPADCCAQoCggEBANRPiZDBTvLxgaxFUALjcuo9XI65f82UaMTRP0xb
1KEzqMIVQsZuyC9MEdyidxbmAw/tnyfv7hmj8sFP8nWc5ceg5ftSJI3lSextRZlz
JkGf15kFe800Vni9/qrW36uTZ8dgaUubHHVme88VS9GmDTtPi55p8AG5+XrHtgMR
tPikm0xHKU9g9WyBrA8Vg84Uao5WHth2keIT/5VmZHkrQ7HErQiRPhDQdCqNqoqB
M6IVeM6sx/TIXuIbdY20g7v1PRLMhTOZK1P9cE+lJ6Fo6xMT7h5zeVNsWUjbtdYE
Kadd8xpXwgva7XBZi8Xaz1FmsjeED09KlYzAWvkjUPDrsacCAwEAAaOCAiowggIm
MB8GA1UdIwQYMBaAFEAkGj2pMXqFd3o9nnKTOYTlQDgZMB0GA1UdDgQWBBR8VdNA
sAkYc3h1hQJjOw4gG1G67TALBgNVHQ8EBAMCBPAwHQYDVR0lBBYwFAYIKwYBBQUH
AwIGCCsGAQUFBwMEMBEGCWCGSAGG+EIBAQQEAwIFoDBuBgNVHSAEZzBlMGMGCisG
AQQBtWuHagowVTAoBggrBgEFBQcCARYcaHR0cDovL3d3dy5hY2VwdGEuY29tL0NQ
Uy1HMzApBggrBgEFBQcCAjAdMBYWD0FjZXB0YS5jb20gUy5BLjADAgEJGgNUQkQw
WgYDVR0SBFMwUaAYBggrBgEEAcEBAqAMFgo5NjkxOTA1MC04oCQGCCsGAQUFBwgD
oBgwFgwKOTY5MTkwNTAtOAYIKwYBBAHBAQKBD2luZm9AYWNlcHRhLmNvbTBfBgNV
HREEWDBWoBcGCCsGAQQBwQEBoAsWCTM2MTUwODYtNqAjBggrBgEFBQcIA6AXMBUM
CTM2MTUwODYtNgYIKwYBBAHBAQKBFklORk9WSUJSQURPU0BHTUFJTC5DT00wPwYI
KwYBBQUHAQEEMzAxMC8GCCsGAQUFBzABhiNodHRwOi8vb2NzcC5hY2VwdGEuY29t
L0NsYXNlM0Jpby1HMzA3BgNVHR8EMDAuMCygKqAohiZodHRwOi8vY3JsLmFjZXB0
YS5jb20vQ2xhc2UzQmlvLUczLmNybDANBgkqhkiG9w0BAQUFAAOCAQEA5glFPIYl
U46mZopX2UZMbpycGXBOOldQvn4mSHaOIadwqoS3MS2zKq6yNYyStzBw8/V7zzOB
C/PR2xXKLZ0F0RvsorvaYen9UJexIw9jqYeBaoJouzIWxngDmJ88NjIM8i2Nq8Dj
0dTX5to8y5z3+j2IErIt1PS4/FPU8ijq9vLBRG+QIbPlvvlejksxQss+crENQ6yB
SrVN5o0wylC+bQ8/d1Tw/DZubHthEZ4ZEx0VpNbh/yO8nfLJ53k/gejAUDXubc5v
3kepNlruRPiJtwFuxDyorJAHVBlRLqraORuHd/NM5m/9DrSXIox+PHOw7xfCmHI9
mrPfGW7p6Y6JNQ==</X509Certificate></X509Data></KeyInfo></Signature></DTE>
  </SetDTE>
<Signature xmlns="http://www.w3.org/2000/09/xmldsig#"><SignedInfo xmlns="http://www.w3.org/2000/09/xmldsig#" xmlns:xsi="http://www.w3.org/2001/XMLSchema-instance"><CanonicalizationMethod Algorithm="http://www.w3.org/TR/2001/REC-xml-c14n-20010315"/><SignatureMethod Algorithm="http://www.w3.org/2000/09/xmldsig#rsa-sha1"/><Reference URI="#SetDoc"><Transforms><Transform Algorithm="http://www.w3.org/2000/09/xmldsig#enveloped-signature"/></Transforms><DigestMethod Algorithm="http://www.w3.org/2000/09/xmldsig#sha1"/><DigestValue>MvB1NSoP3isXQfy7L02qds1Ebfc=</DigestValue></Reference></SignedInfo><SignatureValue>h7w67dac8VR+ViB78r52rzho3H3rDz93nPqBvU9rYWM4w+Xi7/jHCVpueAVz2HNn
Wr7BhuCvvDUw5OsGQ/kQ33n2vOm2StbKSokXne8KLKlqLUVTNn/eRVF0s020Qi7R
OtY2ZfP6wdLQX0Jg1ivnfN7leMsC6LwZkYOQ7Gy93fh8ljDjhd0peQD2w77YtdIy
easgB8/TseoLuBdqTOBdwyBtQhqaaf5KWEm98apLZzIu2gXhFMYMnjxMkSuy/nS3
0Oj3yIwpGmCsdGb35JUYkdhTAXKAWwCipUeRR+lrbtiOJVjhWZXkTxqKMq5FWOW3
6jfFm6OczszjNKAcE9fh9A==</SignatureValue><KeyInfo><KeyValue><RSAKeyValue><Modulus>1E+JkMFO8vGBrEVQAuNy6j1cjrl/zZRoxNE/TFvUoTOowhVCxm7IL0wR3KJ3FuYD
D+2fJ+/uGaPywU/ydZzlx6Dl+1IkjeVJ7G1FmXMmQZ/XmQV7zTRWeL3+qtbfq5Nn
x2BpS5scdWZ7zxVL0aYNO0+LnmnwAbn5ese2AxG0+KSbTEcpT2D1bIGsDxWDzhRq
jlYe2HaR4hP/lWZkeStDscStCJE+ENB0Ko2qioEzohV4zqzH9Mhe4ht1jbSDu/U9
EsyFM5krU/1wT6UnoWjrExPuHnN5U2xZSNu11gQpp13zGlfCC9rtcFmLxdrPUWay
N4QPT0qVjMBa+SNQ8Ouxpw==</Modulus><Exponent>AQAB</Exponent></RSAKeyValue></KeyValue><X509Data><X509Certificate>MIIF1jCCBL6gAwIBAgICZ34wDQYJKoZIhvcNAQEFBQAwgaYxCzAJBgNVBAYTAkNM
MRgwFgYDVQQKEw9BY2VwdGEuY29tIFMuQS4xSDBGBgNVBAMTP0FjZXB0YS5jb20g
QXV0b3JpZGFkIENlcnRpZmljYWRvcmEgQ2xhc2UgMiBQZXJzb25hIE5hdHVyYWwg
LSBHMzEeMBwGCSqGSIb3DQEJARYPaW5mb0BhY2VwdGEuY29tMRMwEQYDVQQFEwo5
NjkxOTA1MC04MB4XDTE2MDcxODE5MzA1MVoXDTE5MDcxODE5MzA1MVowgYYxCzAJ
BgNVBAYTAkNMMRgwFgYDVQQMEw9QRVJTT05BIE5BVFVSQUwxIjAgBgNVBAMTGVZJ
VEVSQk8gQkFSUklFTlRPUyBBWk9DQVIxJTAjBgkqhkiG9w0BCQEWFklORk9WSUJS
QURPU0BHTUFJTC5DT00xEjAQBgNVBAUTCTM2MTUwODYtNjCCASIwDQYJKoZIhvcN
AQEBBQADggEPADCCAQoCggEBANRPiZDBTvLxgaxFUALjcuo9XI65f82UaMTRP0xb
1KEzqMIVQsZuyC9MEdyidxbmAw/tnyfv7hmj8sFP8nWc5ceg5ftSJI3lSextRZlz
JkGf15kFe800Vni9/qrW36uTZ8dgaUubHHVme88VS9GmDTtPi55p8AG5+XrHtgMR
tPikm0xHKU9g9WyBrA8Vg84Uao5WHth2keIT/5VmZHkrQ7HErQiRPhDQdCqNqoqB
M6IVeM6sx/TIXuIbdY20g7v1PRLMhTOZK1P9cE+lJ6Fo6xMT7h5zeVNsWUjbtdYE
Kadd8xpXwgva7XBZi8Xaz1FmsjeED09KlYzAWvkjUPDrsacCAwEAAaOCAiowggIm
MB8GA1UdIwQYMBaAFEAkGj2pMXqFd3o9nnKTOYTlQDgZMB0GA1UdDgQWBBR8VdNA
sAkYc3h1hQJjOw4gG1G67TALBgNVHQ8EBAMCBPAwHQYDVR0lBBYwFAYIKwYBBQUH
AwIGCCsGAQUFBwMEMBEGCWCGSAGG+EIBAQQEAwIFoDBuBgNVHSAEZzBlMGMGCisG
AQQBtWuHagowVTAoBggrBgEFBQcCARYcaHR0cDovL3d3dy5hY2VwdGEuY29tL0NQ
Uy1HMzApBggrBgEFBQcCAjAdMBYWD0FjZXB0YS5jb20gUy5BLjADAgEJGgNUQkQw
WgYDVR0SBFMwUaAYBggrBgEEAcEBAqAMFgo5NjkxOTA1MC04oCQGCCsGAQUFBwgD
oBgwFgwKOTY5MTkwNTAtOAYIKwYBBAHBAQKBD2luZm9AYWNlcHRhLmNvbTBfBgNV
HREEWDBWoBcGCCsGAQQBwQEBoAsWCTM2MTUwODYtNqAjBggrBgEFBQcIA6AXMBUM
CTM2MTUwODYtNgYIKwYBBAHBAQKBFklORk9WSUJSQURPU0BHTUFJTC5DT00wPwYI
KwYBBQUHAQEEMzAxMC8GCCsGAQUFBzABhiNodHRwOi8vb2NzcC5hY2VwdGEuY29t
L0NsYXNlM0Jpby1HMzA3BgNVHR8EMDAuMCygKqAohiZodHRwOi8vY3JsLmFjZXB0
YS5jb20vQ2xhc2UzQmlvLUczLmNybDANBgkqhkiG9w0BAQUFAAOCAQEA5glFPIYl
U46mZopX2UZMbpycGXBOOldQvn4mSHaOIadwqoS3MS2zKq6yNYyStzBw8/V7zzOB
C/PR2xXKLZ0F0RvsorvaYen9UJexIw9jqYeBaoJouzIWxngDmJ88NjIM8i2Nq8Dj
0dTX5to8y5z3+j2IErIt1PS4/FPU8ijq9vLBRG+QIbPlvvlejksxQss+crENQ6yB
SrVN5o0wylC+bQ8/d1Tw/DZubHthEZ4ZEx0VpNbh/yO8nfLJ53k/gejAUDXubc5v
3kepNlruRPiJtwFuxDyorJAHVBlRLqraORuHd/NM5m/9DrSXIox+PHOw7xfCmHI9
mrPfGW7p6Y6JNQ==</X509Certificate></X509Data></KeyInfo></Signature></EnvioDTE>
